polly_textfile_cli/__init__.py
polly_textfile_cli/main.py
polly_textfile_cli-0.1.1.dist-info/METADATA
polly_textfile_cli-0.1.1.dist-info/WHEEL
polly_textfile_cli-0.1.1.dist-info/entry_points.txt
polly_textfile_cli-0.1.1.dist-info/top_level.txt
polly_textfile_cli-0.1.1.dist-info/RECORD
